desmospy/__init__.py
desmospy-0.0.5.dist-info/LICENSE
desmospy-0.0.5.dist-info/METADATA
desmospy-0.0.5.dist-info/WHEEL
desmospy-0.0.5.dist-info/top_level.txt
desmospy-0.0.5.dist-info/RECORD
