Metadata-Version: 2.2
Name: desmospy
Version: 0.0.5
Summary: pythonic desmos
Author-email: Tim DeChant <145816069+timdechant@users.noreply.github.com>
Project-URL: Homepage, https://github.com/timdechant/desmospy
Project-URL: Issues, https://github.com/timdechant/desmospy/issues
Classifier: Programming Language :: Python :: 3
Classifier: License :: OSI Approved :: MIT License
Classifier: Operating System :: OS Independent
Requires-Python: >=3.8
License-File: LICENSE
Requires-Dist: sympy>=1.8
